[
    {
        "transactionName": "StartPage",
        "rawStartTime": 1702110090753,
        "rawEndTime": 1702110091005
    },
    {
        "transactionName": "Login",
        "rawStartTime": 1702110091055,
        "rawEndTime": 1702110091270
    },
    {
        "transactionName": "Flights",
        "rawStartTime": 1702110091302,
        "rawEndTime": 1702110091516
    },
    {
        "transactionName": "FindFlight",
        "rawStartTime": 1702110091549,
        "rawEndTime": 1702110091565
    },
    {
        "transactionName": "Find Flight",
        "rawStartTime": 1702110091586,
        "rawEndTime": 1702110091733
    },
    {
        "transactionName": "ChooseFlight",
        "rawStartTime": 1702110091770,
        "rawEndTime": 1702110091910
    },
    {
        "transactionName": "ChooseFlight",
        "rawStartTime": 1702110091942,
        "rawEndTime": 1702110092066
    },
    {
        "transactionName": "Logout",
        "rawStartTime": 1702110092101,
        "rawEndTime": 1702110092269
    },
    {
        "transactionName": "UC7_BookingFlight",
        "rawStartTime": 1702110090738,
        "rawEndTime": 1702110092299
    }
]